algernon/__init__.py
algernon/alg_date.py
algernon/alg_obj.py
algernon/serializers.py
algernon/aws/__init__.py
algernon/aws/bullhorn.py
algernon/aws/gql.py
algernon/aws/kinetics.py
algernon/aws/lambda_logging.py
algernon/aws/matryoshka.py
algernon/aws/operator.py
algernon/aws/ruffians.py
algernon/aws/snakes.py
algernon/aws/squirrel.py
algernon/aws/task_setup.py
algernon/aws/trident/__init__.py
algernon/aws/trident/connections.py
algernon/aws/trident/trident_driver.py
algernon/aws/trident/trident_obj.py
tests/__init__.py
tests/conftest.py
tests/test_bullhorn.py
tests/test_gql.py
tests/test_squirrel.py
moncrief-7.0.0.dist-info/LICENSE
moncrief-7.0.0.dist-info/METADATA
moncrief-7.0.0.dist-info/WHEEL
moncrief-7.0.0.dist-info/top_level.txt
moncrief-7.0.0.dist-info/RECORD
