Metadata-Version: 2.1
Name: moncrief
Version: 7.0.0
Summary: everything to run a project in a distributed and serverless fashion
Home-page: https://github.com/AlgernonSolutions/algernon
Author: algernon_solutions/jcubeta
Author-email: jcubeta@algernon.solutions
License: GNU Affero General Public License v3.0
Platform: UNKNOWN
Classifier: Programming Language :: Python :: 3
Classifier: License :: OSI Approved :: GNU Affero General Public License v3
Classifier: Operating System :: OS Independent
Requires-Python: >=3.6.0
Requires-Dist: aws-xray-sdk
Requires-Dist: boto3
Requires-Dist: botocore
Requires-Dist: certifi
Requires-Dist: chardet
Requires-Dist: docutils
Requires-Dist: future
Requires-Dist: idna
Requires-Dist: jmespath
Requires-Dist: jsonpickle
Requires-Dist: jsonref
Requires-Dist: python-dateutil
Requires-Dist: python-rapidjson
Requires-Dist: pytz
Requires-Dist: requests
Requires-Dist: s3transfer
Requires-Dist: six
Requires-Dist: urllib3
Requires-Dist: wrapt
Requires-Dist: pytest
